bloomsays/__init__.py
bloomsays/__main__.py
bloomsays/bubble.py
bloomsays/wisdom.py
bloomsays-0.2.5.dist-info/licenses/LICENSE
bloomsays-0.2.5.dist-info/METADATA
bloomsays-0.2.5.dist-info/WHEEL
bloomsays-0.2.5.dist-info/entry_points.txt
bloomsays-0.2.5.dist-info/top_level.txt
bloomsays-0.2.5.dist-info/RECORD
