Metadata-Version: 2.4
Name: bloomsays
Version: 0.2.5
Summary: A package that gives quotes from the professor
Author-email: Howard Appel <hna2019@nyu.edu>, Kazi Hossain <keh8423@nyu.edu>, Luna Suzuki <las9963@nyu.edu>, Tawhid Zaman <tnz8738@nyu.edu>, Jack Chen <jc11462@nyu.edu>
License:                     GNU GENERAL PUBLIC LICENSE
Project-URL: Homepage, https://github.com/swe-students-fall2025/3-python-package-team_orchid
Project-URL: Repository, https://github.com/swe-students-fall2025/3-python-package-team_orchid.git
Keywords: python,package,build,lighthearted
Classifier: Programming Language :: Python :: 3
Classifier: Intended Audience :: Education
Classifier: License :: OSI Approved :: GNU General Public License v3 (GPLv3)
Classifier: Operating System :: OS Independent
Requires-Python: >=3.7
License-File: LICENSE
Provides-Extra: dev
Requires-Dist: pytest; extra == "dev"
Dynamic: license-file
